rajo/__init__.py
rajo/_foreach.py
rajo/_lazy.py
rajo/_trainer.py
rajo/amp.py
rajo/distributed.py
rajo/driver.py
rajo/infer.py
rajo/optim.py
rajo/plot.py
rajo/py.typed
rajo/sched.py
rajo/util.py
rajo/data/__init__.py
rajo/data/_loader.py
rajo/data/_sampler.py
rajo/data/_serialization.py
rajo/metrics/__init__.py
rajo/metrics/base.py
rajo/metrics/confusion.py
rajo/metrics/func.py
rajo/metrics/raw.py
rajo/metrics/roc.py
rajo/nn/__init__.py
rajo/nn/functional.py
rajo/nn/ops.py
rajo/nn/proto.py
rajo/nn/modules/__init__.py
rajo/nn/modules/aggregates.py
rajo/nn/modules/context.py
rajo/nn/modules/conv.py
rajo/nn/modules/head.py
rajo/nn/modules/lazy.py
rajo/nn/modules/loss.py
rajo/nn/modules/primitive.py
rajo/nn/modules/transformer.py
rajo/nn/modules/util.py
rajo/nn/modules/vision.py
rajo/transforms/__init__.py
rajo/transforms/classes.py
rajo/transforms/core.py
rajo/transforms/functional/__init__.py
rajo/transforms/functional/core.py
rajo/transforms/functional/numba.py
rajo-0.3.2.dist-info/METADATA
rajo-0.3.2.dist-info/WHEEL
rajo-0.3.2.dist-info/licenses/LICENSE
rajo-0.3.2.dist-info/RECORD
