Metadata-Version: 2.4
Name: rajo
Version: 0.3.2
Summary: Pytorch training utilities and models
Project-URL: homepage, https://github.com/arquolo/rajo
Author-email: Paul Maevskikh <arquolo@gmail.com>
Maintainer-email: Paul Maevskikh <arquolo@gmail.com>
License: MIT License
License-File: LICENSE
Classifier: Development Status :: 3 - Alpha
Classifier: License :: OSI Approved :: MIT License
Classifier: Operating System :: OS Independent
Classifier: Programming Language :: Python :: 3
Classifier: Programming Language :: Python :: 3.12
Requires-Python: >=3.12
Requires-Dist: einops
Requires-Dist: glow~=0.15.0
Requires-Dist: numpy<3,>=1.21
Requires-Dist: opencv-python-headless~=4.0
Requires-Dist: packaging
Requires-Dist: pynvml~=11.4
Requires-Dist: scipy
Requires-Dist: torchvision~=0.19
Requires-Dist: torch~=2.4
Requires-Dist: tqdm
Provides-Extra: all
Requires-Dist: graphviz; extra == 'all'
Requires-Dist: matplotlib; extra == 'all'
Provides-Extra: dev
Requires-Dist: black~=25.1; extra == 'dev'
Requires-Dist: flake8-alphabetize; extra == 'dev'
Requires-Dist: flake8-pie; extra == 'dev'
Requires-Dist: flake8-pyi; extra == 'dev'
Requires-Dist: flake8-pyproject; extra == 'dev'
Requires-Dist: flake8-simplify; extra == 'dev'
Requires-Dist: flake8~=7.0; extra == 'dev'
Requires-Dist: isort; extra == 'dev'
Requires-Dist: mypy~=1.17; extra == 'dev'
Requires-Dist: pytest~=8.0; extra == 'dev'
Requires-Dist: ruff~=0.12.2; extra == 'dev'
Provides-Extra: dev-core
Requires-Dist: black~=25.1; extra == 'dev-core'
Requires-Dist: flake8-pie; extra == 'dev-core'
Requires-Dist: flake8-pyi; extra == 'dev-core'
Requires-Dist: flake8-pyproject; extra == 'dev-core'
Requires-Dist: flake8-simplify; extra == 'dev-core'
Requires-Dist: flake8~=7.0; extra == 'dev-core'
Requires-Dist: isort; extra == 'dev-core'
Requires-Dist: mypy~=1.17; extra == 'dev-core'
Requires-Dist: pytest~=8.0; extra == 'dev-core'
Requires-Dist: ruff~=0.12.2; extra == 'dev-core'
Provides-Extra: dev-wemake
Requires-Dist: black~=25.1; extra == 'dev-wemake'
Requires-Dist: flake8-pie; extra == 'dev-wemake'
Requires-Dist: flake8-pyi; extra == 'dev-wemake'
Requires-Dist: flake8-pyproject; extra == 'dev-wemake'
Requires-Dist: flake8-simplify; extra == 'dev-wemake'
Requires-Dist: flake8~=7.0; extra == 'dev-wemake'
Requires-Dist: isort; extra == 'dev-wemake'
Requires-Dist: mypy~=1.17; extra == 'dev-wemake'
Requires-Dist: pytest~=8.0; extra == 'dev-wemake'
Requires-Dist: ruff~=0.12.2; extra == 'dev-wemake'
Requires-Dist: wemake-python-styleguide~=1.3.0; extra == 'dev-wemake'
Provides-Extra: dither
Requires-Dist: numba; extra == 'dither'
Provides-Extra: graph
Requires-Dist: graphviz; extra == 'graph'
Provides-Extra: trt
Requires-Dist: torch-tensorrt; extra == 'trt'
